mplcanvas/__init__.py
mplcanvas/figure.py
mplcanvas/py.typed
mplcanvas/pyplot.py
mplcanvas/render.py
mplcanvas/toolbar.py
mplcanvas/utils.py
mplcanvas-25.10.0.dist-info/licenses/LICENSE
mplcanvas-25.10.0.dist-info/METADATA
mplcanvas-25.10.0.dist-info/WHEEL
mplcanvas-25.10.0.dist-info/top_level.txt
mplcanvas-25.10.0.dist-info/RECORD
