Metadata-Version: 2.4
Name: mplcanvas
Version: 25.10.0
Summary: Matplotlib clone that draws on an ipycanvas
Author: Scipp contributors
License-Expression: BSD-3-Clause
Project-URL: Bug Tracker, https://github.com/scipp/mplcanvas/issues
Project-URL: Documentation, https://scipp.github.io/mplcanvas
Project-URL: Source, https://github.com/scipp/mplcanvas
Classifier: Intended Audience :: Science/Research
Classifier: Natural Language :: English
Classifier: Operating System :: OS Independent
Classifier: Programming Language :: Python :: 3
Classifier: Programming Language :: Python :: 3 :: Only
Classifier: Programming Language :: Python :: 3.11
Classifier: Programming Language :: Python :: 3.12
Classifier: Programming Language :: Python :: 3.13
Classifier: Topic :: Scientific/Engineering
Classifier: Typing :: Typed
Requires-Python: >=3.11
License-File: LICENSE
Requires-Dist: matplotlib
Requires-Dist: ipycanvas
Provides-Extra: test
Requires-Dist: pytest; extra == "test"
Dynamic: license-file
